optini/__init__.py
optini/optini.py
optini-0.5.0.dist-info/LICENSE
optini-0.5.0.dist-info/WHEEL
optini-0.5.0.dist-info/METADATA
optini-0.5.0.dist-info/RECORD
