Metadata-Version: 2.1
Name: optini
Version: 0.5.0
Summary: Class to get options from command line and config file
Home-page: https://github.com/datagazing/optini
Author: Brendan Strejcek
Author-email: brendan@datagazing.com
Requires-Python: >=3.7
Classifier: License :: OSI Approved :: MIT License
Requires-Dist: attrs
Requires-Dist: dotmap
